epiccrypto
