Metadata-Version: 2.1
Name: epiccrypto
Version: 0.1.2.3
Summary: Encryption is cool
Author: Epic099
Author-email: 
Classifier: Programming Language :: Python :: 3
Classifier: License :: OSI Approved :: MIT License
Classifier: Operating System :: OS Independent
Requires-Python: >=3.6
Requires-Dist: epicfilemanager
